{"\u7de9\u7de9\u4e0b\u8dcc": "list1", "\u4e0b\u8dccing": "list2", "\u5f88\u5f31": "list3", "\u7de9\u7de9\u4e0a\u6f32": "list4", "\u4e0a\u6f32ing": "list5", "\u5f88\u5f37": "list6", "list1": [{"name": "\u53f0\u5851-\u25ce", "value": -7.51}, {"name": "\u5357\u4e9e-\u25ce", "value": -15.94}, {"name": "\u5112\u9d3b-\u25ce", "value": -6.21}, {"name": "\u83ef\u57ce", "value": -10.0}, {"name": "\u4e09\u967d\u5de5\u696d", "value": -6.34}, {"name": "\u5149\u5bf6\u79d1-\u25ce", "value": -7.33}, {"name": "\u9d3b\u6d77-\u25ce", "value": -33.79}, {"name": "\u5ee3\u9054-\u25ce", "value": -11.22}, {"name": "\u6f22\u5510-\u25ce", "value": -8.91}, {"name": "\u6f64\u6cf0\u5168-\u25ce", "value": -6.09}, {"name": "\u6587\u66c4-\u25ce", "value": -6.65}, {"name": "\u4e16\u82af-KY", "value": -18.83}, {"name": "\u8b5c\u745e-KY", "value": -11.05}, {"name": "\u69ae\u525b-\u25ce", "value": -5.98}, {"name": "\u7fa4\u806f-\u25cf", "value": -25.66}], "list2": [], "list3": [{"name": "\u4e2d\u83ef", "value": -10.53}, {"name": "\u5357\u4e9e\u79d1-\u25ce", "value": -6.9}, {"name": "\u6b23\u8208-\u25ce", "value": -13.25}, {"name": "\u7def\u5275-\u25ce", "value": -42.64}, {"name": "\u6750\u6599-KY", "value": -6.52}], "list4": [{"name": "\u7f8e\u6642-\u25ce", "value": -9.51}, {"name": "\u82f1\u696d\u9054-\u25ce", "value": -16.83}, {"name": "\u745e\u6631-\u25cf", "value": -11.73}, {"name": "\u7fa4\u5275-\u25ce", "value": -6.06}], "list5": [], "list6": []}