{"\u7de9\u7de9\u4e0b\u8dcc": "list1", "\u4e0b\u8dccing": "list2", "\u5f88\u5f31": "list3", "\u7de9\u7de9\u4e0a\u6f32": "list4", "\u4e0a\u6f32ing": "list5", "\u5f88\u5f37": "list6", "list1": [{"name": "\u4e2d\u92fc-\u25ce", "value": -6.04}, {"name": "\u53f0\u7a4d\u96fb-\u25cf", "value": -517.28}, {"name": "\u5bcc\u90a6\u91d1-\u25ce", "value": -19.15}, {"name": "\u7389\u5c71\u91d1-\u25ce", "value": -5.34}], "list2": [{"name": "\u4e0a\u9280-\u25cf", "value": -7.08}, {"name": "\u9d3b\u6d77-\u25ce", "value": -73.28}, {"name": "\u806f\u767c\u79d1-\u25cf", "value": -42.4}, {"name": "\u9577\u69ae-\u25ce", "value": -12.71}, {"name": "\u967d\u660e-\u25ce", "value": -10.16}, {"name": "\u570b\u6cf0\u91d1-\u25ce", "value": -6.98}, {"name": "\u51f1\u57fa\u91d1-\u25ce", "value": -18.38}, {"name": "\u5143\u5927\u91d1-\u25ce", "value": -14.18}, {"name": "\u53f0\u65b0\u91d1-\u25ce", "value": -9.02}, {"name": "\u5927\u7acb\u5149-\u25cf", "value": -11.84}, {"name": "\u7fa4\u5275-\u25ce", "value": -11.97}, {"name": "\u65e5\u6708\u5149\u6295\u63a7-\u25ce", "value": -6.34}, {"name": "\u7fa4\u806f-\u25cf", "value": -7.54}], "list3": [{"name": "\u83ef\u78a9-\u25cf", "value": -13.88}, {"name": "\u65b0\u65e5\u8208-\u25ce", "value": -6.82}], "list4": [], "list5": [], "list6": []}