{"\u7de9\u7de9\u4e0b\u8dcc": "list1", "\u4e0b\u8dccing": "list2", "\u5f88\u5f31": "list3", "\u7de9\u7de9\u4e0a\u6f32": "list4", "\u4e0a\u6f32ing": "list5", "\u5f88\u5f37": "list6", "list1": [{"name": "\u83ef\u57ce", "value": -9.87}, {"name": "\u9d3b\u6d77-\u25ce", "value": -233.89}, {"name": "\u570b\u5de8-\u25cf", "value": -15.61}, {"name": "\u53f0\u7a4d\u96fb-\u25cf", "value": -417.0}, {"name": "\u5927\u540c-\u25ce", "value": -15.98}, {"name": "\u6280\u5609-\u25cf", "value": -13.84}, {"name": "\u5ee3\u9054-\u25ce", "value": -125.29}, {"name": "\u53cb\u9054-\u25ce", "value": -5.57}, {"name": "\u806f\u767c\u79d1-\u25cf", "value": -17.1}, {"name": "\u9577\u69ae-\u25ce", "value": -67.24}, {"name": "\u967d\u660e-\u25ce", "value": -9.66}, {"name": "\u5bcc\u90a6\u91d1-\u25ce", "value": -7.53}, {"name": "\u570b\u6cf0\u91d1-\u25ce", "value": -25.38}, {"name": "\u51f1\u57fa\u91d1-\u25ce", "value": -6.42}, {"name": "\u7d71\u4e00\u8d85", "value": -10.52}, {"name": "\u5927\u7acb\u5149-\u25cf", "value": -6.39}, {"name": "\u4e9e\u5149-\u25ce", "value": -14.72}, {"name": "\u6b23\u8208-\u25ce", "value": -23.06}, {"name": "\u7def\u5275-\u25ce", "value": -28.13}, {"name": "\u920a\u8c61-\u25cf", "value": -14.93}, {"name": "\u96d9\u9d3b-\u25ce", "value": -16.37}, {"name": "\u7389\u6676\u5149-\u25cf", "value": -11.73}, {"name": "\u529b\u65fa-\u25cf", "value": -5.39}, {"name": "\u795e\u9054-\u25ce", "value": -14.4}, {"name": "\u65e5\u6708\u5149\u6295\u63a7-\u25ce", "value": -9.37}, {"name": "\u4fe1\u9a4a-\u25cf", "value": -8.48}, {"name": "\u4e2d\u79df-KY-\u25ce", "value": -6.8}, {"name": "\u77fd\u529b*-KY", "value": -6.75}], "list2": [{"name": "\u91d1\u50cf\u96fb-\u25ce", "value": -8.76}, {"name": "\u5947\u92d0-\u25cf", "value": -67.4}, {"name": "\u667a\u539f-\u25ce", "value": -12.23}, {"name": "\u5275\u610f-\u25cf", "value": -9.58}, {"name": "\u5065\u7b56-\u25cf", "value": -16.36}, {"name": "\u4e16\u82af-KY", "value": -12.62}, {"name": "\u8b5c\u745e-KY", "value": -5.01}, {"name": "\u4e2d\u7f8e\u6676-\u25ce", "value": -12.79}, {"name": "\u842c\u6f64", "value": -9.84}, {"name": "\u548c\u693f", "value": -6.48}, {"name": "\u74b0\u7403\u6676-\u25cf", "value": -8.79}, {"name": "\u7def\u7a4e-\u25cf", "value": -7.83}, {"name": "\u6607\u967d\u534a\u5c0e\u9ad4", "value": -12.29}], "list3": [{"name": "\u7687\u660c", "value": -5.83}], "list4": [{"name": "\u4e2d\u83ef\u96fb-\u25ce", "value": -11.55}, {"name": "\u53ef\u6210-\u25ce", "value": -5.27}, {"name": "\u5104\u8c50", "value": -6.15}], "list5": [{"name": "\u7cfb\u5fae", "value": -7.35}], "list6": []}